<?xml version="1.0" encoding="UTF-8"?>
<objects serializationModel="Studio.01.10.00">
    <object class="AudioFile" id="{7f2e6f18-3ee6-4c3d-9e34-0a45065b4a0f}">
        <property name="assetPath">
            <value>bulletimpact1.wav</value>
        </property>
        <property name="frequencyInKHz">
            <value>44.0999985</value>
        </property>
        <property name="channelCount">
            <value>2</value>
        </property>
        <property name="length">
            <value>1.393015873015873</value>
        </property>
        <relationship name="masterAssetFolder">
            <destination>{3da5290c-ecaa-4645-a48c-079b03f4f748}</destination>
        </relationship>
    </object>
</objects>
